{
  "domain": "https://walletinvestor.com",
  "manual_emails": [
    "naomi@walletinvestor.com"
  ],
  "gpt_emails": [
    "naomi@walletinvestor.com"
  ],
  "token_usage": {
    "tokens_used": 986,
    "summarize_calls": 1,
    "estimated_cost_usd": 0.00493
  },
  "matches_expected": {
    "manual": true,
    "gpt": true,
    "form": false
  },
  "used_recovery": false,
  "timed_out": false,
  "form_detected": true,
  "form_page_urls": [
    "https://advertise.walletinvestor.com/"
  ],
  "chosen_form": {
    "page_url": "https://advertise.walletinvestor.com/",
    "summary": "",
    "fields": [
      {
        "tag": "input",
        "type": "email",
        "name": "form_fields[email]",
        "id": "form-field-email",
        "required": true,
        "placeholder": "Email",
        "autocomplete": "",
        "maxlength": "",
        "pattern": "",
        "class": [
          "elementor-field",
          "elementor-size-sm",
          "elementor-field-textual"
        ],
        "style": "",
        "label": "Email"
      },
      {
        "tag": "textarea",
        "type": "textarea",
        "name": "form_fields[message]",
        "id": "form-field-message",
        "required": false,
        "placeholder": "Message",
        "autocomplete": "",
        "maxlength": "",
        "pattern": "",
        "class": [
          "elementor-field-textual",
          "elementor-field",
          "elementor-size-sm"
        ],
        "style": "",
        "label": "Message"
      }
    ],
    "submit_button": "<button class=\"elementor-button elementor-size-sm\" type=\"submit\">\n<span>\n<span class=\"elementor-button-icon\">\n</span>\n<span class=\"elementor-button-text\">Send</span>\n</span>\n</button>"
  },
  "added_unrequired_textareas": [
    {
      "tag": "textarea",
      "type": "textarea",
      "name": "form_fields[message]",
      "id": "form-field-message",
      "required": false,
      "placeholder": "Message",
      "autocomplete": "",
      "maxlength": "",
      "pattern": "",
      "class": [
        "elementor-field-textual",
        "elementor-field",
        "elementor-size-sm"
      ],
      "style": "",
      "label": "Message"
    }
  ]
}